moodley/__init__.py
moodley/__main__.py
moodley/api.py
moodley/background.py
moodley/calendar_utils.py
moodley/core.py
moodley/helpers.py
moodley/main.py
moodley/models.py
moodley-1.0.0.dist-info/licenses/LICENSE
moodley-1.0.0.dist-info/METADATA
moodley-1.0.0.dist-info/WHEEL
moodley-1.0.0.dist-info/entry_points.txt
moodley-1.0.0.dist-info/top_level.txt
moodley-1.0.0.dist-info/RECORD
