Metadata-Version: 2.4
Name: moodley
Version: 1.0.0
Summary: Moodley CLI — Sync Moodle assignment deadlines to Google Calendar
Author-email: Faheem12005 <mohdfaheem.1205@gmail.com>
License-Expression: MIT
Project-URL: Homepage, https://github.com/Faheem12005/moodley
Project-URL: Issues, https://github.com/Faheem12005/moodley/issues
Project-URL: Documentation, https://github.com/Faheem12005/moodley#readme
Project-URL: Source, https://github.com/Faheem12005/moodley
Keywords: LMS,VITOL,Google Calendar,CLI,VIT
Classifier: Programming Language :: Python :: 3
Classifier: Operating System :: OS Independent
Requires-Python: >=3.10
License-File: LICENSE
Requires-Dist: google-api-python-client
Requires-Dist: google-auth
Requires-Dist: google-auth-oauthlib
Requires-Dist: requests
Requires-Dist: pydantic
Requires-Dist: questionary
Requires-Dist: keyring
Requires-Dist: platformdirs
Requires-Dist: beautifulsoup4
Dynamic: license-file
